conflator/__init__.py
conflator/conflator.py
conflator-0.1.7.dist-info/LICENSE.md
conflator-0.1.7.dist-info/METADATA
conflator-0.1.7.dist-info/WHEEL
conflator-0.1.7.dist-info/RECORD
