Metadata-Version: 2.3
Name: conflator
Version: 0.1.7
Summary: Load small app configurations from environment variables, command line arguments and config files, according to a pydantic model.
License: Apache-2.0
Author: James Hawkes
Author-email: James.Hawkes@ecmwf.int
Requires-Python: >3.9
Classifier: License :: OSI Approved :: Apache Software License
Classifier: Programming Language :: Python :: 3
Classifier: Programming Language :: Python :: 3.10
Classifier: Programming Language :: Python :: 3.11
Classifier: Programming Language :: Python :: 3.12
Classifier: Programming Language :: Python :: 3.13
Requires-Dist: argparse (>1.0)
Requires-Dist: pydantic (>2.0)
Requires-Dist: pytest (>8.0)
Requires-Dist: pyyaml (>6.0)
Requires-Dist: rich-argparse (>1.0)
Project-URL: Repository, https://github.com/ecmwf/conflator/
